{
  "site_title": "最新国产电视剧-最新剧集片库-高清剧集在线播放",
  "logo_name": "高清剧集片库",
  "records": 2000,
  "categories": 10,
  "featured": [
    "昨夜情深",
    "冲动杀人 儿子呵!",
    "魔鬼终结者2立体版",
    "恋爱兵法",
    "准新娘",
    "我们长大了"
  ],
  "hls_urls": [
    "https://customer-7t103rn8rocxo5v6.cloudflarestream.com/e398cb38b257828eeedbcaa0ae2856da/manifest/video.m3u8",
    "https://customer-7t103rn8rocxo5v6.cloudflarestream.com/77ae15566dde5cfb920bae4712a38399/manifest/video.m3u8",
    "https://customer-7t103rn8rocxo5v6.cloudflarestream.com/41cb67b47a3668efaea014219666e659/manifest/video.m3u8"
  ]
}